<?xml version="1.0" encoding="UTF-8"?>
<!DOCTYPE mapper PUBLIC "-//mybatis.org//DTD Mapper 3.0//EN" "http://mybatis.org/dtd/mybatis-3-mapper.dtd">
<mapper namespace="org.ysu.ckqaback.mapper.QaRetrievalLogsMapper">

    <!-- 通用查询映射结果 -->
    <resultMap id="BaseResultMap" type="org.ysu.ckqaback.entity.QaRetrievalLogs">
        <id column="id" property="id" />
        <result column="session_id" property="sessionId" />
        <result column="course_id" property="courseId" />
        <result column="index_run_id" property="indexRunId" />
        <result column="query_mode" property="queryMode" />
        <result column="query_text" property="queryText" />
        <result column="retrieval_status" property="retrievalStatus" />
        <result column="error_message" property="errorMessage" />
        <result column="created_at" property="createdAt" />
    </resultMap>

    <!-- 通用查询结果列 -->
    <sql id="Base_Column_List">
        id, session_id, course_id, index_run_id, query_mode, query_text, retrieval_status, error_message, created_at
    </sql>

</mapper>
